swdata/__init__.py
swdata/__version__.py
swdata/core.py
swdata-0.0.2.dist-info/METADATA
swdata-0.0.2.dist-info/WHEEL
swdata-0.0.2.dist-info/top_level.txt
swdata-0.0.2.dist-info/RECORD
