Metadata-Version: 2.1
Name: swdata
Version: 0.0.2
Summary: data
Home-page: 
Author: sw
Author-email: 
License: MIT
Classifier: Programming Language :: Python :: 3
Classifier: License :: OSI Approved :: MIT License
Classifier: Operating System :: OS Independent
Requires-Python: >=3.6, <4
Requires-Dist: netifaces >=0.11.0
Requires-Dist: django-redis >=5.0.0
